{"repo": {"timestamp": 1614239661000, "version": 21, "name": "My First F-Droid Repo Demo", "icon": "fdroid-icon.png", "address": "http://localhost/fdroid/repo", "description": "This is a repository of apps to be used with F-Droid. Applications in this repository are either official binaries built by the original application developers, or are binaries built from source by the admin of f-droid.org using the tools on https://gitlab.com/u/fdroid. "}, "requests": {"install": [], "uninstall": []}, "apps": [{"authorName": "Bushers Electronics", "categories": ["fdroid"], "suggestedVersionCode": "2147483647", "license": "Unknown", "name": "AC Sample App", "added": 1614230104000, "icon": "ms.appcenter.sampleapp.android.3.png", "packageName": "ms.appcenter.sampleapp.android", "lastUpdated": 1614230104000}, {"authorName": "Bushers Electronics", "categories": ["fdroid"], "suggestedVersionCode": "2147483647", "license": "Unknown", "name": "BUSHERS TVSDT", "added": 1614230104000, "packageName": "com.bushers.tvsdt", "lastUpdated": 1614230104000}, {"authorName": "Bushers Electronics", "categories": ["fdroid"], "suggestedVersionCode": "2147483647", "license": "Unknown", "name": "TVSDT Wireless", "added": 1614230103000, "icon": "com.bushers.tvsdt.wireless.17.png", "packageName": "com.bushers.tvsdt.wireless", "lastUpdated": 1614230103000}], "packages": {"com.bushers.tvsdt": [{"added": 1614230104000, "apkName": "tvsdt.apk", "hash": "d1e8fa6ed71153d69a2348da327da63e69349b03a507bdaf158e289960092bd4", "hashType": "sha256", "minSdkVersion": 21, "packageName": "com.bushers.tvsdt", "sig": "c1043c778bc92bfe3d753a0b15bf32f0", "signer": "81761aa7a73975dd8f653fc8a60cb84f15d45f993244b9152487036aed42f121", "size": 1283413, "targetSdkVersion": 30, "uses-permission": [["android.permission.INTERNET", null], ["android.permission.ACCESS_NETWORK_STATE", null], ["android.permission.FOREGROUND_SERVICE", null]], "versionCode": 9, "versionName": "1.0"}], "com.bushers.tvsdt.wireless": [{"added": 1614230103000, "apkName": "tvsdt-wireless.apk", "hash": "62fbc56c09dc3da59492883fac60d70d04ea62a3d1526a453943240e7f2c87b8", "hashType": "sha256", "minSdkVersion": 21, "packageName": "com.bushers.tvsdt.wireless", "sig": "c1043c778bc92bfe3d753a0b15bf32f0", "signer": "81761aa7a73975dd8f653fc8a60cb84f15d45f993244b9152487036aed42f121", "size": 1542349, "targetSdkVersion": 30, "uses-permission": [["android.permission.INTERNET", null], ["android.permission.ACCESS_NETWORK_STATE", null], ["android.permission.FOREGROUND_SERVICE", null], ["android.permission.BLUETOOTH", null], ["android.permission.BLUETOOTH_ADMIN", null], ["android.permission.REQUEST_INSTALL_PACKAGES", null], ["android.permission.DOWNLOAD_WITHOUT_NOTIFICATION", null]], "versionCode": 17, "versionName": "1.0"}], "ms.appcenter.sampleapp.android": [{"added": 1614230104000, "apkName": "tvsm.apk", "hash": "c1c79f604bf94db1be5eb9e88118b3c570c5c6cb2426fc5ef6001a14454795e0", "hashType": "sha256", "minSdkVersion": 21, "packageName": "ms.appcenter.sampleapp.android", "sig": "c1043c778bc92bfe3d753a0b15bf32f0", "signer": "81761aa7a73975dd8f653fc8a60cb84f15d45f993244b9152487036aed42f121", "size": 1694445, "targetSdkVersion": 30, "uses-permission": [["android.permission.REQUEST_INSTALL_PACKAGES", null], ["android.permission.DOWNLOAD_WITHOUT_NOTIFICATION", null], ["android.permission.INTERNET", null], ["android.permission.ACCESS_NETWORK_STATE", null]], "versionCode": 3, "versionName": "1.0"}]}}